eoap_cwlwrap/__about__.py
eoap_cwlwrap/__init__.py
eoap_cwlwrap/builder.py
eoap_cwlwrap/types.py
eoap_cwlwrap-0.23.0.dist-info/METADATA
eoap_cwlwrap-0.23.0.dist-info/WHEEL
eoap_cwlwrap-0.23.0.dist-info/entry_points.txt
eoap_cwlwrap-0.23.0.dist-info/licenses/LICENSE
eoap_cwlwrap-0.23.0.dist-info/licenses/NOTICE
eoap_cwlwrap-0.23.0.dist-info/RECORD
