Metadata-Version: 2.4
Name: eoap_cwlwrap
Version: 0.23.0
Summary: Add stage-in/stage-out steps to EOAP CWL Workflows
Project-URL: Documentation, https://github.com/EOEPCA/eoap-cwlwrap#readme
Project-URL: Issues, https://github.com/EOEPCA/eoap-cwlwrap/issues
Project-URL: Source, https://github.com/EOEPCA/eoap-cwlwrap
Author-email: Fabrice Brito <fabrice.brito@terradue.com>, Simone Tripodi <simone.tripodi@terradue.com>
License-Expression: Apache-2.0
License-File: LICENSE
License-File: NOTICE
Classifier: Development Status :: 4 - Beta
Classifier: Environment :: Console
Classifier: Intended Audience :: Developers
Classifier: Programming Language :: Python
Classifier: Programming Language :: Python :: 3.9
Classifier: Programming Language :: Python :: 3.10
Classifier: Programming Language :: Python :: 3.11
Classifier: Programming Language :: Python :: 3.12
Classifier: Programming Language :: Python :: 3.13
Classifier: Programming Language :: Python :: Implementation :: CPython
Classifier: Programming Language :: Python :: Implementation :: PyPy
Requires-Python: >=3.8
Requires-Dist: click>=8.0
Requires-Dist: cwl-loader>=0.14.0
Requires-Dist: cwl-utils>=0.40
Requires-Dist: cwltool>=3.1.20250110105449
Requires-Dist: loguru
